hello_world/__init__.py
hello_world/hello_world.py
hello_user_art256-1.0.0.dist-info/METADATA
hello_user_art256-1.0.0.dist-info/WHEEL
hello_user_art256-1.0.0.dist-info/entry_points.txt
hello_user_art256-1.0.0.dist-info/top_level.txt
hello_user_art256-1.0.0.dist-info/RECORD
